memos_mcp/__init__.py
memos_mcp/__main__.py
memos_mcp/attachment_helpers.py
memos_mcp/batch_ops.py
memos_mcp/client.py
memos_mcp/config.py
memos_mcp/date_parser.py
memos_mcp/exporters.py
memos_mcp/formatters.py
memos_mcp/template_manager.py
memos_mcp/tools.py
memos_mcp_enhanced-0.2.2.dist-info/licenses/LICENSE
memos_mcp_enhanced-0.2.2.dist-info/METADATA
memos_mcp_enhanced-0.2.2.dist-info/WHEEL
memos_mcp_enhanced-0.2.2.dist-info/entry_points.txt
memos_mcp_enhanced-0.2.2.dist-info/top_level.txt
memos_mcp_enhanced-0.2.2.dist-info/RECORD
