Metadata-Version: 2.4
Name: memos-mcp-enhanced
Version: 0.2.2
Summary: Enhanced MCP server for Memos with complete CRUD and search capabilities
Requires-Python: >=3.10
License-File: LICENSE
Requires-Dist: mcp>=1.1.2
Requires-Dist: httpx>=0.27.0
Requires-Dist: pydantic>=2.9.0
Requires-Dist: python-dotenv>=1.0.0
Requires-Dist: pydantic-settings>=2.0.0
Provides-Extra: dev
Requires-Dist: pytest>=8.3.0; extra == "dev"
Requires-Dist: pytest-asyncio>=0.24.0; extra == "dev"
Requires-Dist: ruff>=0.6.0; extra == "dev"
Requires-Dist: mypy>=1.11.0; extra == "dev"
Dynamic: license-file
